[
  {
    "userName": "name1",
    "text": "This is a dummy text",
    "kudos": [],
    "img": "https://www.google.com/images/branding/googlelogo/2x/googlelogo_color_272x92dp.png",
    "createdAt": 1675595886
  },
  {
    "userName": "name1",
    "text": "This is a dummy text",
    "kudos": [],
    "img": "https://www.google.com/images/branding/googlelogo/2x/googlelogo_color_272x92dp.png",
    "createdAt": 1675595887
  },
  {
    "userName": "name1",
    "text": "This is a dummy text",
    "kudos": [],
    "img": "https://www.google.com/images/branding/googlelogo/2x/googlelogo_color_272x92dp.png",
    "createdAt": 1675595888
  },
  {

    "userName":"name2",
    "text": "This is a dummy text",
    "kudos": [],
    "img": "https://www.google.com/images/branding/googlelogo/2x/googlelogo_color_272x92dp.png",
    "createdAt": 1675595889
  },
  {

    "userName": "name2",
    "text": "This is a dummy text",
    "kudos": [],
    "img": "https://www.google.com/images/branding/googlelogo/2x/googlelogo_color_272x92dp.png",
    "createdAt": 1675595890
  },
  {

    "userName": "name2",
    "text": "This is a dummy text",
    "kudos": [],
    "img": "https://www.google.com/images/branding/googlelogo/2x/googlelogo_color_272x92dp.png",
    "createdAt": 1675595891
  },
  {
    "userName": "name3",
    "text": "This is a dummy text",
    "kudos": [],
    "img": "https://www.google.com/images/branding/googlelogo/2x/googlelogo_color_272x92dp.png",
    "createdAt": 1675595892
  },
  {
    "userName": "name3",
    "text": "This is a dummy text",
    "kudos": [],
    "img": "https://www.google.com/images/branding/googlelogo/2x/googlelogo_color_272x92dp.png",
    "createdAt": 1675595893
  },
  {
    "userName": "name3",
    "text": "This is a dummy text",
    "kudos": [],
    "img": "https://www.google.com/images/branding/googlelogo/2x/googlelogo_color_272x92dp.png",
    "createdAt": 1675595894
  }
]
